dapp/__init__.py
dapp/dapp.py
e3interface/__init__.py
e3interface/e3_connector.py
e3interface/e3_encoder.py
e3interface/e3_interface.py
e3interface/e3_logging.py
e3interface/defs/e3.asn
spectrum/__init__.py
spectrum/spectrum_dapp.py
spectrum/defs/e3sm_spectrum.asn
visualization/__init__.py
visualization/dashboard.py
visualization/energy.py
visualization/grafana.py
visualization/influx.py
visualization/iq.py
visualization/templates/index.html
dapps-0.0.5.dist-info/METADATA
dapps-0.0.5.dist-info/WHEEL
dapps-0.0.5.dist-info/licenses/LICENSE
dapps-0.0.5.dist-info/RECORD
