Metadata-Version: 2.4
Name: dapps
Version: 0.0.5
Summary: A library for creating and connecting dApps to Open RAN units.
Project-URL: Homepage, https://openrangym.com/o-ran-frameworks/dapps
Project-URL: Package, https://pypi.org/project/dapps/
Project-URL: Source, https://github.com/wineslab/dApp-library
Project-URL: Bug Tracker, https://github.com/wineslab/dApp-library/issues
Author-email: Andrea Lacava <thecave003@gmail.com>
License-File: LICENSE
Keywords: 5G,O-RAN,cellular,dApps,networks
Classifier: Development Status :: 4 - Beta
Classifier: Programming Language :: Python
Classifier: Programming Language :: Python :: 3.8
Classifier: Programming Language :: Python :: 3.9
Classifier: Programming Language :: Python :: 3.10
Classifier: Programming Language :: Python :: 3.11
Classifier: Programming Language :: Python :: 3.12
Classifier: Programming Language :: Python :: Implementation :: CPython
Classifier: Programming Language :: Python :: Implementation :: PyPy
Requires-Python: >=3.8
Requires-Dist: asn1tools
Requires-Dist: numpy
Requires-Dist: pyzmq
Requires-Dist: typing-extensions
Provides-Extra: all
Requires-Dist: flask; extra == 'all'
Requires-Dist: flask-socketio; extra == 'all'
Requires-Dist: influxdb-client; extra == 'all'
Requires-Dist: libiq; extra == 'all'
Requires-Dist: matplotlib; extra == 'all'
Requires-Dist: pysctp; extra == 'all'
Provides-Extra: api
Requires-Dist: influxdb-client; extra == 'api'
Provides-Extra: cnn
Requires-Dist: libiq; extra == 'cnn'
Provides-Extra: gui
Requires-Dist: flask; extra == 'gui'
Requires-Dist: flask-socketio; extra == 'gui'
Requires-Dist: matplotlib; extra == 'gui'
Provides-Extra: network
Requires-Dist: pysctp; extra == 'network'
